[
    {
        "image": "static/violations/e4f76e7823d0439aa3ae8b13746b1af4.jpg",
        "vehicle": "motorcycle",
        "plate": "Unknown",
        "reason": "No Helmet",
        "time": "25 Mar 2026, 09:34 PM"
    },
    {
        "image": "static/violations/d723f2f4bcf94016ad007310640e94bf.jpg",
        "vehicle": "bus",
        "plate": "Unknown",
        "reason": "No Helmet",
        "time": "25 Mar 2026, 09:34 PM"
    },
    {
        "image": "static/violations/c8d7b3acf0494557a3312bc234b8c26a.jpg",
        "vehicle": "car",
        "plate": "Unknown",
        "reason": "No Helmet",
        "time": "25 Mar 2026, 09:33 PM"
    },
    {
        "image": "static/violations/a397271849cf4fa0be08a007d760b656.jpg",
        "vehicle": "motorcycle",
        "plate": "Unknown",
        "reason": "No Helmet",
        "time": "25 Mar 2026, 09:33 PM"
    },
    {
        "image": "static/violations/377a940c0dee471ab416610492a1d4e1.jpg",
        "vehicle": "bus",
        "plate": "Unknown",
        "reason": "No Helmet",
        "time": "25 Mar 2026, 09:33 PM"
    },
    {
        "image": "static/violations/d99d13e7f186433d9d099861f1e07879.jpg",
        "vehicle": "motorcycle",
        "plate": "Unknown",
        "reason": "No Helmet",
        "time": "25 Mar 2026, 09:33 PM"
    },
    {
        "image": "static/violations/2462d321c14e40c8a50dc26006c63317.jpg",
        "vehicle": "motorcycle",
        "plate": "Unknown",
        "reason": "No Helmet",
        "time": "25 Mar 2026, 09:33 PM"
    },
    {
        "image": "static/violations/25aa2d27505c4985928e844860ee6254.jpg",
        "vehicle": "car",
        "plate": "Unknown",
        "reason": "No Helmet",
        "time": "25 Mar 2026, 09:33 PM"
    },
    {
        "image": "static/violations/f89bd0a565a44801b64cc73a548a81c8.jpg",
        "vehicle": "motorcycle",
        "plate": "Unknown",
        "reason": "No Helmet",
        "time": "25 Mar 2026, 09:33 PM"
    },
    {
        "image": "static/violations/7a90b503cc1c416a8779e06369d00532.jpg",
        "vehicle": "truck",
        "plate": "Unknown",
        "reason": "No Helmet",
        "time": "25 Mar 2026, 09:33 PM"
    },
    {
        "image": "static/violations/b04ec4c030a045f1ae99bf91e24751ef.jpg",
        "vehicle": "car",
        "plate": "Unknown",
        "reason": "No Helmet",
        "time": "25 Mar 2026, 09:33 PM"
    },
    {
        "image": "static/violations/e253ede291834f96838f0292adac1826.jpg",
        "vehicle": "truck",
        "plate": "Unknown",
        "reason": "No Helmet",
        "time": "25 Mar 2026, 09:33 PM"
    },
    {
        "image": "static/violations/03ecebe1edc64b03b91202b0ad89900c.jpg",
        "vehicle": "car",
        "plate": "Unknown",
        "reason": "No Helmet",
        "time": "25 Mar 2026, 09:33 PM"
    },
    {
        "image": "static/violations/6a2e60594a2f47aaada0b43b2986c1e6.jpg",
        "vehicle": "car",
        "plate": "Unknown",
        "reason": "No Helmet",
        "time": "25 Mar 2026, 09:33 PM"
    },
    {
        "image": "static/violations/45c97528409d4593bcfbe2190baed9d9.jpg",
        "vehicle": "bus",
        "plate": "Unknown",
        "reason": "No Helmet",
        "time": "25 Mar 2026, 09:33 PM"
    },
    {
        "image": "static/violations/32444ebc6d7e41528067ca771d164b57.jpg",
        "vehicle": "car",
        "plate": "Unknown",
        "reason": "No Helmet",
        "time": "25 Mar 2026, 09:33 PM"
    },
    {
        "image": "static/violations/88dfbd37c4c94d42906e08745c15f831.jpg",
        "vehicle": "motorcycle",
        "plate": "Unknown",
        "reason": "No Helmet",
        "time": "25 Mar 2026, 09:33 PM"
    },
    {
        "image": "static/violations/51703e42d73e478391d2360d3d91fe03.jpg",
        "vehicle": "truck",
        "plate": "Unknown",
        "reason": "No Helmet",
        "time": "25 Mar 2026, 09:33 PM"
    },
    {
        "image": "static/violations/01c140d7b7894205b3d9f10fbd5880f8.jpg",
        "vehicle": "car",
        "plate": "Unknown",
        "reason": "No Helmet",
        "time": "25 Mar 2026, 09:33 PM"
    },
    {
        "image": "static/violations/0ecd599637e449fc85ebfc69b7890168.jpg",
        "vehicle": "car",
        "plate": "Unknown",
        "reason": "No Helmet",
        "time": "25 Mar 2026, 09:33 PM"
    },
    {
        "image": "static/violations/e99d129cb237441a8244ee741cbd03ff.jpg",
        "vehicle": "motorcycle",
        "plate": "Unknown",
        "reason": "No Helmet",
        "time": "25 Mar 2026, 09:23 PM"
    },
    {
        "image": "static/violations/af96b6e717fd47889492fc34599eb91e.jpg",
        "vehicle": "bus",
        "plate": "Unknown",
        "reason": "No Helmet",
        "time": "25 Mar 2026, 09:22 PM"
    },
    {
        "image": "static/violations/2a2003265bcf46f2ba64640e6c83b2b3.jpg",
        "vehicle": "motorcycle",
        "plate": "Unknown",
        "reason": "No Helmet",
        "time": "25 Mar 2026, 09:22 PM"
    },
    {
        "image": "static/violations/583f54f4b006489dadba3ea27d2dc25c.jpg",
        "vehicle": "motorcycle",
        "plate": "Unknown",
        "reason": "No Helmet",
        "time": "25 Mar 2026, 09:22 PM"
    },
    {
        "image": "static/violations/88db896fd6c6475dacad0fa6b2cb0609.jpg",
        "vehicle": "car",
        "plate": "Unknown",
        "reason": "No Helmet",
        "time": "25 Mar 2026, 09:22 PM"
    },
    {
        "image": "static/violations/6b6d0208a92a4812880158ade8e7a3c4.jpg",
        "vehicle": "motorcycle",
        "plate": "Unknown",
        "reason": "No Helmet",
        "time": "25 Mar 2026, 09:22 PM"
    },
    {
        "image": "static/violations/f511d8fe76ca49b4be80ed1fa5f305a3.jpg",
        "vehicle": "truck",
        "plate": "Unknown",
        "reason": "No Helmet",
        "time": "25 Mar 2026, 09:22 PM"
    },
    {
        "image": "static/violations/7dad393733d641568fe72f82ca2bdf64.jpg",
        "vehicle": "car",
        "plate": "Unknown",
        "reason": "No Helmet",
        "time": "25 Mar 2026, 09:22 PM"
    },
    {
        "image": "static/violations/c8577d65c22a460a88a13e96c638d23a.jpg",
        "vehicle": "truck",
        "plate": "Unknown",
        "reason": "No Helmet",
        "time": "25 Mar 2026, 09:22 PM"
    },
    {
        "image": "static/violations/f0774c646b0a4a159f181af429f15ff2.jpg",
        "vehicle": "car",
        "plate": "Unknown",
        "reason": "No Helmet",
        "time": "25 Mar 2026, 09:22 PM"
    },
    {
        "image": "static/violations/3d8f706d03124b3281f773d57eef595c.jpg",
        "vehicle": "car",
        "plate": "Unknown",
        "reason": "No Helmet",
        "time": "25 Mar 2026, 09:22 PM"
    },
    {
        "image": "static/violations/915d3d4beb0f4fd0ab9f8e2337290ca3.jpg",
        "vehicle": "bus",
        "plate": "Unknown",
        "reason": "No Helmet",
        "time": "25 Mar 2026, 09:22 PM"
    },
    {
        "image": "static/violations/bfb1cf4648eb45f3ac938ea9d6997d5f.jpg",
        "vehicle": "car",
        "plate": "Unknown",
        "reason": "No Helmet",
        "time": "25 Mar 2026, 09:22 PM"
    },
    {
        "image": "static/violations/35185830e6c6427791559e9b32d36da3.jpg",
        "vehicle": "motorcycle",
        "plate": "Unknown",
        "reason": "No Helmet",
        "time": "25 Mar 2026, 09:22 PM"
    },
    {
        "image": "static/violations/a8c8b4bad7844191b13187d57d8af91d.jpg",
        "vehicle": "truck",
        "plate": "Unknown",
        "reason": "No Helmet",
        "time": "25 Mar 2026, 09:22 PM"
    },
    {
        "image": "static/violations/b03983d02911418b9ce9661addcc1e6a.jpg",
        "vehicle": "car",
        "plate": "Unknown",
        "reason": "No Helmet",
        "time": "25 Mar 2026, 09:22 PM"
    },
    {
        "image": "static/violations/163c41ca8c494427a9e77c6fa3c8cceb.jpg",
        "vehicle": "car",
        "plate": "Unknown",
        "reason": "No Helmet",
        "time": "25 Mar 2026, 09:22 PM"
    },
    {
        "image": "static/violations/fc27938d8f734da3a22a4299074e5bdc.jpg",
        "vehicle": "motorcycle",
        "plate": "Unknown",
        "reason": "No Helmet",
        "time": "25 Mar 2026, 09:21 PM"
    },
    {
        "image": "static/violations/d210149b890546de9640d58605b8ea44.jpg",
        "vehicle": "motorcycle",
        "plate": "Unknown",
        "reason": "No Helmet",
        "time": "25 Mar 2026, 09:21 PM"
    },
    {
        "image": "static/violations/de71468d105d412ab64ce583fd2b3c12.jpg",
        "vehicle": "motorcycle",
        "plate": "Unknown",
        "reason": "No Helmet",
        "time": "25 Mar 2026, 09:21 PM"
    },
    {
        "image": "static/violations/4b3a7f61be854a22861fee131ae7212c.jpg",
        "vehicle": "motorcycle",
        "plate": "Unknown",
        "reason": "No Helmet",
        "time": "25 Mar 2026, 09:21 PM"
    },
    {
        "image": "static/violations/ff27e58cb02d46b7b0a6e8c9293007b8.jpg",
        "vehicle": "motorcycle",
        "plate": "Unknown",
        "reason": "No Helmet",
        "time": "25 Mar 2026, 09:21 PM"
    },
    {
        "image": "static/violations/71e82c763f5f41c6acb73cec369e7d89.jpg",
        "vehicle": "motorcycle",
        "plate": "Unknown",
        "reason": "No Helmet",
        "time": "25 Mar 2026, 09:21 PM"
    },
    {
        "image": "static/violations/56e1c4c7e41f44b096fee0fb23b1d6c6.jpg",
        "vehicle": "motorcycle",
        "plate": "Unknown",
        "reason": "No Helmet",
        "time": "25 Mar 2026, 09:21 PM"
    },
    {
        "image": "static/violations/2b30d0b796c14a3f8235bee18a2cfe25.jpg",
        "vehicle": "motorcycle",
        "plate": "Unknown",
        "reason": "No Helmet",
        "time": "25 Mar 2026, 09:20 PM"
    },
    {
        "image": "static/violations/043f80a6512f4040b01151b0485757db.jpg",
        "vehicle": "motorcycle",
        "plate": "Unknown",
        "reason": "No Helmet",
        "time": "25 Mar 2026, 09:20 PM"
    },
    {
        "image": "static/violations/f8d4c6a7fedc46849c2195cf51bc4000.jpg",
        "vehicle": "motorcycle",
        "plate": "Unknown",
        "reason": "No Helmet",
        "time": "25 Mar 2026, 09:20 PM"
    },
    {
        "image": "static/violations/a07da93ab4c540aaadebc0ff8b55030a.jpg",
        "vehicle": "motorcycle",
        "plate": "Unknown",
        "reason": "No Helmet",
        "time": "25 Mar 2026, 09:20 PM"
    },
    {
        "image": "static/violations/962f3634fbfa47a58d7bd8899162f71d.jpg",
        "vehicle": "motorcycle",
        "plate": "Unknown",
        "reason": "No Helmet",
        "time": "25 Mar 2026, 09:20 PM"
    },
    {
        "image": "static/violations/4dba69f3e3464dadbc61b821cc671a14.jpg",
        "vehicle": "motorcycle",
        "plate": "Unknown",
        "reason": "No Helmet",
        "time": "25 Mar 2026, 09:20 PM"
    },
    {
        "image": "static/violations/d03fc9232e2543b6a03e1477574dc1a5.jpg",
        "vehicle": "motorcycle",
        "plate": "Unknown",
        "reason": "No Helmet",
        "time": "25 Mar 2026, 09:20 PM"
    },
    {
        "image": "static/violations/7a4fe4783920427c86c0edd5859ff840.jpg",
        "vehicle": "motorcycle",
        "plate": "Unknown",
        "reason": "No Helmet",
        "time": "25 Mar 2026, 09:20 PM"
    },
    {
        "image": "static/violations/387f65802b3f45c9abae1f90f1892f87.jpg",
        "vehicle": "motorcycle",
        "plate": "Unknown",
        "reason": "No Helmet",
        "time": "25 Mar 2026, 09:20 PM"
    },
    {
        "image": "static/violations/3ec85337236e4c649c12eb501ab3ef0d.jpg",
        "vehicle": "motorcycle",
        "plate": "Unknown",
        "reason": "No Helmet",
        "time": "25 Mar 2026, 09:20 PM"
    },
    {
        "image": "static/violations/25ac928a4ae14c0c872558952f932946.jpg",
        "vehicle": "motorcycle",
        "plate": "Unknown",
        "reason": "No Helmet",
        "time": "25 Mar 2026, 09:20 PM"
    },
    {
        "image": "static/violations/706655850d294784a7ab7182c61c106d.jpg",
        "vehicle": "motorcycle",
        "plate": "Unknown",
        "reason": "No Helmet",
        "time": "25 Mar 2026, 09:20 PM"
    },
    {
        "image": "static/violations/5d47972768e449d0b0f29be13aeea247.jpg",
        "vehicle": "motorcycle",
        "plate": "Unknown",
        "reason": "No Helmet",
        "time": "25 Mar 2026, 09:20 PM"
    },
    {
        "image": "static/violations/9c4033ebc50647f181f2e2664bf09093.jpg",
        "vehicle": "motorcycle",
        "plate": "Unknown",
        "reason": "No Helmet",
        "time": "25 Mar 2026, 09:20 PM"
    },
    {
        "image": "static/violations/f150fa7bee664530b28c37a1b3824359.jpg",
        "vehicle": "motorcycle",
        "plate": "Unknown",
        "reason": "No Helmet",
        "time": "25 Mar 2026, 09:20 PM"
    },
    {
        "image": "static/violations/65bc776fa7d54bd48ce73cf4edc095b4.jpg",
        "vehicle": "motorcycle",
        "plate": "Unknown",
        "reason": "No Helmet",
        "time": "25 Mar 2026, 09:20 PM"
    },
    {
        "image": "static/violations/0c11c7406f884a688266f344cbd4efbc.jpg",
        "vehicle": "motorcycle",
        "plate": "Unknown",
        "reason": "No Helmet",
        "time": "25 Mar 2026, 09:20 PM"
    },
    {
        "image": "static/violations/443403c73393455486e8bcb0d7e55c87.jpg",
        "vehicle": "motorcycle",
        "plate": "Unknown",
        "reason": "No Helmet",
        "time": "25 Mar 2026, 09:20 PM"
    },
    {
        "image": "static/violations/bb0a6c3ca90f4333b203a48a37b394fb.jpg",
        "vehicle": "motorcycle",
        "plate": "Unknown",
        "reason": "No Helmet",
        "time": "25 Mar 2026, 09:20 PM"
    },
    {
        "image": "static/violations/27230b5be9494af08a6b5fee38a030f3.jpg",
        "vehicle": "motorcycle",
        "plate": "Unknown",
        "reason": "No Helmet",
        "time": "25 Mar 2026, 09:20 PM"
    },
    {
        "image": "static/violations/de252aea37974421b108cb8bb77db105.jpg",
        "vehicle": "motorcycle",
        "plate": "Unknown",
        "reason": "No Helmet",
        "time": "25 Mar 2026, 09:20 PM"
    },
    {
        "image": "static/violations/cbd67be36c744b77a6c9dcd0e16123e4.jpg",
        "vehicle": "motorcycle",
        "plate": "Unknown",
        "reason": "No Helmet",
        "time": "25 Mar 2026, 09:20 PM"
    },
    {
        "image": "static/violations/3c6d103a43ba43ebb7c5f410df61ac45.jpg",
        "vehicle": "motorcycle",
        "plate": "Unknown",
        "reason": "No Helmet",
        "time": "25 Mar 2026, 09:20 PM"
    },
    {
        "image": "static/violations/934370d08768434f91331fbc96431205.jpg",
        "vehicle": "motorcycle",
        "plate": "Unknown",
        "reason": "No Helmet",
        "time": "25 Mar 2026, 09:20 PM"
    },
    {
        "image": "static/violations/968eff97272542b3be4eb279e7e96c9d.jpg",
        "vehicle": "motorcycle",
        "plate": "Unknown",
        "reason": "No Helmet",
        "time": "25 Mar 2026, 09:20 PM"
    },
    {
        "image": "static/violations/b3d86cb5ceaa43e6abad4b0489e51bdd.jpg",
        "vehicle": "motorcycle",
        "plate": "Unknown",
        "reason": "No Helmet",
        "time": "25 Mar 2026, 09:20 PM"
    },
    {
        "image": "static/violations/727349e0572b43fb99c18eba53e0809b.jpg",
        "vehicle": "motorcycle",
        "plate": "Unknown",
        "reason": "No Helmet",
        "time": "25 Mar 2026, 09:20 PM"
    },
    {
        "image": "static/violations/71f0ebcb607c414e804d91cedbb1e813.jpg",
        "vehicle": "motorcycle",
        "plate": "Unknown",
        "reason": "No Helmet",
        "time": "25 Mar 2026, 09:20 PM"
    },
    {
        "image": "static/violations/48ba9ba78f3f42e2a4de660641740060.jpg",
        "vehicle": "motorcycle",
        "plate": "Unknown",
        "reason": "No Helmet",
        "time": "25 Mar 2026, 09:20 PM"
    },
    {
        "image": "static/violations/9ffb5ba08734429ca1a4db3047363c7f.jpg",
        "vehicle": "motorcycle",
        "plate": "Unknown",
        "reason": "No Helmet",
        "time": "25 Mar 2026, 09:20 PM"
    },
    {
        "image": "static/violations/1396bc66b9a644e7aeb4ee67027964f8.jpg",
        "vehicle": "motorcycle",
        "plate": "Unknown",
        "reason": "No Helmet",
        "time": "25 Mar 2026, 09:20 PM"
    },
    {
        "image": "static/violations/4cc36c815ba349e4920225a2b27964d8.jpg",
        "vehicle": "motorcycle",
        "plate": "Unknown",
        "reason": "No Helmet",
        "time": "25 Mar 2026, 09:20 PM"
    },
    {
        "image": "static/violations/6deb5d4a312e44b583b78a4b6f354713.jpg",
        "vehicle": "motorcycle",
        "plate": "Unknown",
        "reason": "No Helmet",
        "time": "25 Mar 2026, 09:20 PM"
    },
    {
        "image": "static/violations/5caa5fd1dfc74e799c7e917d3b3f4a2a.jpg",
        "vehicle": "motorcycle",
        "plate": "Unknown",
        "reason": "No Helmet",
        "time": "25 Mar 2026, 09:19 PM"
    },
    {
        "image": "static/violations/f2733a25b59d43319bced2c53d10e484.jpg",
        "vehicle": "motorcycle",
        "plate": "Unknown",
        "reason": "No Helmet",
        "time": "25 Mar 2026, 09:19 PM"
    },
    {
        "image": "static/violations/dca0975cdcac4e1296003a2a0d81b00d.jpg",
        "vehicle": "motorcycle",
        "plate": "Unknown",
        "reason": "No Helmet",
        "time": "25 Mar 2026, 09:19 PM"
    },
    {
        "image": "static/violations/dfd3ed48064945d8b683d0db91b218a2.jpg",
        "vehicle": "motorcycle",
        "plate": "Unknown",
        "reason": "No Helmet",
        "time": "25 Mar 2026, 09:19 PM"
    },
    {
        "image": "static/violations/de151600d1fe4911a3d8571fc1b6bd4b.jpg",
        "vehicle": "motorcycle",
        "plate": "Unknown",
        "reason": "No Helmet",
        "time": "25 Mar 2026, 09:19 PM"
    },
    {
        "image": "static/violations/38debbf0b7e241689459149235df7924.jpg",
        "vehicle": "motorcycle",
        "plate": "Unknown",
        "reason": "No Helmet",
        "time": "25 Mar 2026, 09:19 PM"
    },
    {
        "image": "static/violations/46857fb1e69c4b6d98bf643a0722d1e1.jpg",
        "vehicle": "motorcycle",
        "plate": "Unknown",
        "reason": "No Helmet",
        "time": "25 Mar 2026, 09:19 PM"
    },
    {
        "image": "static/violations/e759020f7bfa44c993e5ad3a9229c35a.jpg",
        "vehicle": "motorcycle",
        "plate": "Unknown",
        "reason": "No Helmet",
        "time": "25 Mar 2026, 09:19 PM"
    },
    {
        "image": "static/violations/39b05a91336c4213a8519f161f231538.jpg",
        "vehicle": "motorcycle",
        "plate": "Unknown",
        "reason": "No Helmet",
        "time": "25 Mar 2026, 09:19 PM"
    },
    {
        "image": "static/violations/18e044d6acbc4fa3b939c1f62027a36c.jpg",
        "vehicle": "motorcycle",
        "plate": "Unknown",
        "reason": "No Helmet",
        "time": "25 Mar 2026, 09:19 PM"
    },
    {
        "image": "static/violations/259f8e02f20042ffb7664e661da24eb3.jpg",
        "vehicle": "motorcycle",
        "plate": "Unknown",
        "reason": "No Helmet",
        "time": "25 Mar 2026, 09:19 PM"
    },
    {
        "image": "static/violations/98bb35b10686408db5fd3e467486904b.jpg",
        "vehicle": "motorcycle",
        "plate": "Unknown",
        "reason": "No Helmet",
        "time": "25 Mar 2026, 09:19 PM"
    },
    {
        "image": "static/violations/ee0429d28a7645bfa6befb3a8920f96c.jpg",
        "vehicle": "motorcycle",
        "plate": "Unknown",
        "reason": "No Helmet",
        "time": "25 Mar 2026, 09:19 PM"
    },
    {
        "image": "static/violations/d52ec56d8f7c45a6ba7e8a43a139c8e3.jpg",
        "vehicle": "motorcycle",
        "plate": "Unknown",
        "reason": "No Helmet",
        "time": "25 Mar 2026, 09:19 PM"
    }
]